[
  {
    "timerange": "20250202-20260203",
    "market_change": "-22.14%",
    "trades": "81",
    "avg_profit_pct": "-0.58",
    "total_profit_usdt": "-1484.387",
    "total_profit_pct": "-14.84",
    "avg_duration": "1 day, 19:47:00",
    "win_draw_loss": "24    54     3  29.6",
    "drawdown": "1587.24 USDT  15.85%",
    "name": "all_data_1yr"
  },
  {
    "timerange": "20251106-20260203",
    "market_change": "-24.21%",
    "trades": "29",
    "avg_profit_pct": "-0.51",
    "total_profit_usdt": "-496.649",
    "total_profit_pct": "-4.97",
    "avg_duration": "15:43:00",
    "win_draw_loss": "10    18     1  34.5",
    "drawdown": "595.431 USDT  5.95%",
    "name": "last_90d"
  },
  {
    "timerange": "20251205-20260203",
    "market_change": "-14.84%",
    "trades": "20",
    "avg_profit_pct": "0.15",
    "total_profit_usdt": "99.063",
    "total_profit_pct": "0.99",
    "avg_duration": "13:36:00",
    "win_draw_loss": "7    13     0   100",
    "drawdown": "0 USDT  0.00%",
    "name": "last_60d"
  },
  {
    "timerange": "20260104-20260203",
    "market_change": "-13.64%",
    "trades": "12",
    "avg_profit_pct": "0.22",
    "total_profit_usdt": "86.008",
    "total_profit_pct": "0.86",
    "avg_duration": "16:37:00",
    "win_draw_loss": "5     7     0   100",
    "drawdown": "0 USDT  0.00%",
    "name": "last_30d"
  }
]